{
 "etype": "<type 'exceptions.ImportError'>", 
 "evalue": "ImportError('No module named sales_invoice.sales_invoice',)", 
 "exception": {
  "args": "('No module named sales_invoice.sales_invoice',)", 
  "message": "'No module named sales_invoice.sales_invoice'"
 }, 
 "frames": [
  {
   "call": "(request=<Request 'http://192.168.1.160/' [POST]>)", 
   "dump": {
    "frappe. handler": "<module 'frappe.handler' from '/home/frappe/frappe-bench/apps/frappe/frappe/handler.pyc'>", 
    "frappe.handler. handle": "<function handle>", 
    "global frappe": "<module 'frappe' from '/home/frappe/frappe-bench/apps/frappe/frappe/__init__.pyc'>", 
    "response": "None"
   }, 
   "file": "/home/frappe/frappe-bench/apps/frappe/frappe/app.py", 
   "func": "application", 
   "lines": {
    "53": "", 
    "54": "\t\tif frappe.local.form_dict.cmd:", 
    "55": "\t\t\tresponse = frappe.handler.handle()", 
    "56": "", 
    "57": "\t\telif frappe.request.path.startswith(\"/api/\"):"
   }, 
   "lnum": 55
  }, 
  {
   "call": "()", 
   "dump": {
    "cmd": "u'erpnext.accounts.doctype.sales_invoice.sales_invoice.get_bank_cash_account'", 
    "global execute_cmd": "<function execute_cmd>"
   }, 
   "file": "/home/frappe/frappe-bench/apps/frappe/frappe/handler.py", 
   "func": "handle", 
   "lines": {
    "17": "", 
    "18": "\tif cmd!='login':", 
    "19": "\t\texecute_cmd(cmd)", 
    "20": "", 
    "21": "\treturn build_response(\"json\")"
   }, 
   "lnum": 19
  }, 
  {
   "call": "(cmd=u'erpnext.accounts.doctype.sales_invoice.sales_invoice.get_bank_cash_account', from_async=False)", 
   "dump": {
    "cmd": "u'erpnext.accounts.doctype.sales_invoice.sales_invoice.get_bank_cash_account'", 
    "global get_attr": "<function get_attr>", 
    "method": "undefined"
   }, 
   "file": "/home/frappe/frappe-bench/apps/frappe/frappe/handler.py", 
   "func": "execute_cmd", 
   "lines": {
    "28": "\t\tbreak", 
    "29": "", 
    "30": "\tmethod = get_attr(cmd)", 
    "31": "\tif from_async:", 
    "32": "\t\tmethod = method.queue"
   }, 
   "lnum": 30
  }, 
  {
   "call": "(cmd=u'erpnext.accounts.doctype.sales_invoice.sales_invoice.get_bank_cash_account')", 
   "dump": {
    "cmd": "u'erpnext.accounts.doctype.sales_invoice.sales_invoice.get_bank_cash_account'", 
    "frappe. get_attr": "<function get_attr>", 
    "global frappe": "<module 'frappe' from '/home/frappe/frappe-bench/apps/frappe/frappe/__init__.pyc'>", 
    "method": "undefined"
   }, 
   "file": "/home/frappe/frappe-bench/apps/frappe/frappe/handler.py", 
   "func": "get_attr", 
   "lines": {
    "112": "\t\"\"\"get method object from cmd\"\"\"", 
    "113": "\tif '.' in cmd:", 
    "114": "\t\tmethod = frappe.get_attr(cmd)", 
    "115": "\telse:", 
    "116": "\t\tmethod = globals()[cmd]"
   }, 
   "lnum": 114
  }, 
  {
   "call": "(method_string=u'erpnext.accounts.doctype.sales_invoice.sales_invoice.get_bank_cash_account')", 
   "dump": {
    "builtin getattr": "<built-in function getattr>", 
    "global get_module": "<function get_module>", 
    "methodname": "u'get_bank_cash_account'", 
    "modulename": "u'erpnext.accounts.doctype.sales_invoice.sales_invoice'"
   }, 
   "file": "/home/frappe/frappe-bench/apps/frappe/frappe/__init__.py", 
   "func": "get_attr", 
   "lines": {
    "857": "\tmodulename = '.'.join(method_string.split('.')[:-1])", 
    "858": "\tmethodname = method_string.split('.')[-1]", 
    "859": "\treturn getattr(get_module(modulename), methodname)", 
    "860": "", 
    "861": "def call(fn, *args, **kwargs):"
   }, 
   "lnum": 859
  }, 
  {
   "call": "(modulename=u'erpnext.accounts.doctype.sales_invoice.sales_invoice')", 
   "dump": {
    "global importlib": "<module 'importlib' from '/usr/lib/python2.7/importlib/__init__.pyc'>", 
    "importlib. import_module": "<function import_module>", 
    "modulename": "u'erpnext.accounts.doctype.sales_invoice.sales_invoice'"
   }, 
   "file": "/home/frappe/frappe-bench/apps/frappe/frappe/__init__.py", 
   "func": "get_module", 
   "lines": {
    "641": "def get_module(modulename):", 
    "642": "\t\"\"\"Returns a module object for given Python module name using `importlib.import_module`.\"\"\"", 
    "643": "\treturn importlib.import_module(modulename)", 
    "644": "", 
    "645": "def scrub(txt):"
   }, 
   "lnum": 643
  }, 
  {
   "call": "(name=u'erpnext.accounts.doctype.sales_invoice.sales_invoice', package=None)", 
   "dump": {
    "builtin __import__": "<built-in function __import__>", 
    "name": "u'erpnext.accounts.doctype.sales_invoice.sales_invoice'"
   }, 
   "file": "/usr/lib/python2.7/importlib/__init__.py", 
   "func": "import_module", 
   "lines": {
    "34": "                break", 
    "35": "            level += 1", 
    "36": "        name = _resolve_name(name[level:], package, level)", 
    "37": "    __import__(name)", 
    "38": "    return sys.modules[name]"
   }, 
   "lnum": 37
  }
 ], 
 "locals": {
  "name": "u'erpnext.accounts.doctype.sales_invoice.sales_invoice'", 
  "package": "None"
 }, 
 "pyver": "Python 2.7.6: /home/frappe/frappe-bench/env/bin/python (prefix: /home/frappe/frappe-bench/env)", 
 "timestamp": "2017-02-07 16:14:59.047749", 
 "traceback": "Traceback (most recent call last):\n  File \"/home/frappe/frappe-bench/apps/frappe/frappe/app.py\", line 55, in application\n    response = frappe.handler.handle()\n  File \"/home/frappe/frappe-bench/apps/frappe/frappe/handler.py\", line 19, in handle\n    execute_cmd(cmd)\n  File \"/home/frappe/frappe-bench/apps/frappe/frappe/handler.py\", line 30, in execute_cmd\n    method = get_attr(cmd)\n  File \"/home/frappe/frappe-bench/apps/frappe/frappe/handler.py\", line 114, in get_attr\n    method = frappe.get_attr(cmd)\n  File \"/home/frappe/frappe-bench/apps/frappe/frappe/__init__.py\", line 859, in get_attr\n    return getattr(get_module(modulename), methodname)\n  File \"/home/frappe/frappe-bench/apps/frappe/frappe/__init__.py\", line 643, in get_module\n    return importlib.import_module(modulename)\n  File \"/usr/lib/python2.7/importlib/__init__.py\", line 37, in import_module\n    __import__(name)\nImportError: No module named sales_invoice.sales_invoice\n"
}